rlab_cli/__init__.py
rlab_cli/cli.py
rlab_cli/core.py
rlab_cli/main.py
rlab_cli/platform.py
rlab_cli-1.0.0.dist-info/METADATA
rlab_cli-1.0.0.dist-info/WHEEL
rlab_cli-1.0.0.dist-info/entry_points.txt
rlab_cli-1.0.0.dist-info/top_level.txt
rlab_cli-1.0.0.dist-info/RECORD
