Metadata-Version: 2.4
Name: rlab-cli
Version: 1.0.0
Summary: RLab Platform CLI - Digital Twins for Educational Robotics powered by Nueroid
Author-email: RLab Team <rlab@rosversity.com>
License: MIT
Project-URL: Homepage, https://github.com/Rosversity/rlab-cli
Project-URL: Documentation, https://github.com/Rosversity/rlab-cli#readme
Project-URL: Repository, https://github.com/Rosversity/rlab-cli.git
Project-URL: Issues, https://github.com/Rosversity/rlab-cli/issues
Keywords: digital-twins,robotics,education,nueroid,rlab
Classifier: Development Status :: 4 - Beta
Classifier: Intended Audience :: Education
Classifier: Intended Audience :: Science/Research
Classifier: License :: OSI Approved :: MIT License
Classifier: Operating System :: OS Independent
Classifier: Programming Language :: Python :: 3
Classifier: Programming Language :: Python :: 3.8
Classifier: Programming Language :: Python :: 3.9
Classifier: Programming Language :: Python :: 3.10
Classifier: Programming Language :: Python :: 3.11
Classifier: Programming Language :: Python :: 3.12
Classifier: Topic :: Education
Classifier: Topic :: Scientific/Engineering :: Artificial Intelligence
Requires-Python: >=3.8
